{
  "minecraft:recipes/combat/leather_helmet": {
    "criteria": {
      "has_leather": "2026-02-13 00:24:56 +0000"
    },
    "done": true
  },
  "minecraft:recipes/combat/iron_leggings": {
    "criteria": {
      "has_iron_ingot": "2026-02-13 00:10:14 +0000"
    },
    "done": true
  },
  "vanilla_refresh:player/hurt": {
    "criteria": {
      "requirement": "2026-02-13 00:26:46 +0000"
    },
    "done": true
  },
  "minecraft:recipes/combat/leather_leggings": {
    "criteria": {
      "has_leather": "2026-02-13 00:24:56 +0000"
    },
    "done": true
  },
  "vanilla_refresh:biome/deep_dark": {
    "criteria": {
      "requirement": "2026-02-13 00:00:25 +0000"
    },
    "done": true
  },
  "minecraft:end/kill_dragon": {
    "criteria": {
      "killed_dragon": "2026-02-13 00:19:12 +0000"
    },
    "done": true
  },
  "adorablehamsterpets:husbandry/root": {
    "criteria": {
      "always_unlock": "2026-02-13 00:00:16 +0000"
    },
    "done": true
  },
  "blood_n_particles:oh_my_blood": {
    "criteria": {
      "requirement": "2026-02-13 00:01:49 +0000"
    },
    "done": true
  },
  "minecraft:recipes/combat/iron_chestplate": {
    "criteria": {
      "has_iron_ingot": "2026-02-13 00:10:14 +0000"
    },
    "done": true
  },
  "minecraft:recipes/decorations/oak_sign": {
    "criteria": {
      "has_planks": "2026-02-13 00:01:16 +0000"
    },
    "done": true
  },
  "minecraft:recipes/redstone/oak_trapdoor": {
    "criteria": {
      "has_planks": "2026-02-13 00:01:16 +0000"
    },
    "done": true
  },
  "minecraft:recipes/misc/iron_nugget": {
    "criteria": {
      "has_iron_ingot": "2026-02-13 00:10:14 +0000"
    },
    "done": true
  },
  "vanilla_refresh:location/the_end": {
    "criteria": {
      "requirement": "2026-02-13 00:03:31 +0000"
    },
    "done": true
  },
  "minecraft:recipes/misc/bucket": {
    "criteria": {
      "has_iron_ingot": "2026-02-13 00:10:14 +0000"
    },
    "done": true
  },
  "minecraft:recipes/combat/iron_helmet": {
    "criteria": {
      "has_iron_ingot": "2026-02-13 00:10:14 +0000"
    },
    "done": true
  },
  "minecraft:recipes/transportation/minecart": {
    "criteria": {
      "has_iron_ingot": "2026-02-13 00:10:14 +0000"
    },
    "done": true
  },
  "minecraft:recipes/tools/iron_hoe": {
    "criteria": {
      "has_iron_ingot": "2026-02-13 00:10:14 +0000"
    },
    "done": true
  },
  "vanilla_refresh:biome/jungle": {
    "criteria": {
      "requirement": "2026-02-13 00:20:55 +0000"
    },
    "done": true
  },
  "minecraft:recipes/combat/leather_chestplate": {
    "criteria": {
      "has_leather": "2026-02-13 00:24:56 +0000"
    },
    "done": true
  },
  "minecraft:adventure/shoot_arrow": {
    "criteria": {
      "shot_arrow": "2026-02-13 00:08:06 +0000"
    },
    "done": true
  },
  "minecraft:story/smelt_iron": {
    "criteria": {
      "iron": "2026-02-13 00:10:14 +0000"
    },
    "done": true
  },
  "minecraft:recipes/decorations/crafting_table": {
    "criteria": {
      "unlock_right_away": "2026-02-13 00:00:15 +0000"
    },
    "done": true
  },
  "minecraft:recipes/decorations/chest": {
    "criteria": {
      "has_lots_of_items": "2026-02-13 00:00:40 +0000"
    },
    "done": true
  },
  "minecraft:recipes/tools/shears": {
    "criteria": {
      "has_iron_ingot": "2026-02-13 00:10:14 +0000"
    },
    "done": true
  },
  "minecraft:recipes/misc/stick": {
    "criteria": {
      "has_planks": "2026-02-13 00:01:16 +0000"
    },
    "done": true
  },
  "minecraft:recipes/building_blocks/emerald_block": {
    "criteria": {
      "has_emerald": "2026-02-13 00:24:56 +0000"
    },
    "done": true
  },
  "minecraft:recipes/building_blocks/oak_stairs": {
    "criteria": {
      "has_planks": "2026-02-13 00:01:16 +0000"
    },
    "done": true
  },
  "minecraft:adventure/kill_all_mobs": {
    "criteria": {
      "minecraft:skeleton": "2026-02-13 00:09:31 +0000",
      "minecraft:enderman": "2026-02-13 00:04:43 +0000",
      "minecraft:zombie": "2026-02-13 00:09:13 +0000",
      "minecraft:ender_dragon": "2026-02-13 00:19:12 +0000"
    },
    "done": false
  },
  "minecraft:recipes/decorations/chain": {
    "criteria": {
      "has_iron_ingot": "2026-02-13 00:10:14 +0000"
    },
    "done": true
  },
  "minecraft:recipes/decorations/oak_fence": {
    "criteria": {
      "has_planks": "2026-02-13 00:01:16 +0000"
    },
    "done": true
  },
  "adorablehamsterpets:recipes/combat/hamster_armor_iron_smithing": {
    "criteria": {
      "has_material": "2026-02-13 00:10:14 +0000"
    },
    "done": true
  },
  "minecraft:recipes/building_blocks/iron_block": {
    "criteria": {
      "has_iron_ingot": "2026-02-13 00:10:14 +0000"
    },
    "done": true
  },
  "simplyswords:mjolnir": {
    "criteria": {
      "requirement": "2026-02-13 00:02:13 +0000"
    },
    "done": true
  },
  "minecraft:recipes/misc/bone_meal": {
    "criteria": {
      "has_bone": "2026-02-13 00:01:34 +0000"
    },
    "done": true
  },
  "minecraft:adventure/totem_of_undying": {
    "criteria": {
      "used_totem": "2026-02-13 00:05:28 +0000"
    },
    "done": true
  },
  "lootr:root": {
    "criteria": {
      "always_true": "2026-02-13 00:00:15 +0000"
    },
    "done": true
  },
  "blood_n_particles:blooded_enemies": {
    "criteria": {
      "requirement": "2026-02-13 00:09:07 +0000"
    },
    "done": true
  },
  "minecraft:recipes/decorations/smithing_table": {
    "criteria": {
      "has_iron_ingot": "2026-02-13 00:10:14 +0000"
    },
    "done": true
  },
  "adorablehamsterpets:technical/has_received_initial_guidebook": {
    "criteria": {
      "received": "2026-02-13 00:00:15 +0000"
    },
    "done": true
  },
  "simplyswords:livyatan": {
    "criteria": {
      "requirement": "2026-02-13 00:01:40 +0000"
    },
    "done": true
  },
  "minecraft:recipes/misc/leather_horse_armor": {
    "criteria": {
      "has_leather": "2026-02-13 00:24:56 +0000"
    },
    "done": true
  },
  "vanilla_refresh:player/end_teleport": {
    "criteria": {
      "s3": "2026-02-13 00:26:37 +0000"
    },
    "done": false
  },
  "minecraft:husbandry/root": {
    "criteria": {
      "consumed_item": "2026-02-13 00:01:31 +0000"
    },
    "done": true
  },
  "betterdeserttemples:root": {
    "criteria": {
      "always": "2026-02-13 00:00:15 +0000"
    },
    "done": true
  },
  "minecraft:recipes/redstone/oak_button": {
    "criteria": {
      "has_planks": "2026-02-13 00:01:16 +0000"
    },
    "done": true
  },
  "minecraft:nether/netherite_armor": {
    "criteria": {
      "netherite_armor": "2026-02-13 00:00:40 +0000"
    },
    "done": true
  },
  "minecraft:recipes/combat/iron_sword": {
    "criteria": {
      "has_iron_ingot": "2026-02-13 00:10:14 +0000"
    },
    "done": true
  },
  "minecraft:recipes/tools/iron_pickaxe": {
    "criteria": {
      "has_iron_ingot": "2026-02-13 00:10:14 +0000"
    },
    "done": true
  },
  "minecraft:recipes/combat/shield": {
    "criteria": {
      "has_iron_ingot": "2026-02-13 00:10:14 +0000"
    },
    "done": true
  },
  "minecraft:recipes/redstone/hopper": {
    "criteria": {
      "has_iron_ingot": "2026-02-13 00:10:14 +0000"
    },
    "done": true
  },
  "minecraft:recipes/decorations/iron_bars": {
    "criteria": {
      "has_iron_ingot": "2026-02-13 00:10:14 +0000"
    },
    "done": true
  },
  "minecraft:recipes/building_blocks/oak_slab": {
    "criteria": {
      "has_planks": "2026-02-13 00:01:16 +0000"
    },
    "done": true
  },
  "minecraft:recipes/combat/iron_boots": {
    "criteria": {
      "has_iron_ingot": "2026-02-13 00:10:14 +0000"
    },
    "done": true
  },
  "minecraft:recipes/decorations/lantern": {
    "criteria": {
      "has_iron_ingot": "2026-02-13 00:10:14 +0000"
    },
    "done": true
  },
  "touhou_little_maid:grant_patchouli_book": {
    "criteria": {
      "tick": "2026-02-13 00:00:15 +0000"
    },
    "done": true
  },
  "minecraft:recipes/redstone/oak_fence_gate": {
    "criteria": {
      "has_planks": "2026-02-13 00:01:16 +0000"
    },
    "done": true
  },
  "minecraft:recipes/misc/charcoal": {
    "criteria": {
      "has_log": "2026-02-13 00:00:52 +0000"
    },
    "done": true
  },
  "minecraft:recipes/tools/iron_shovel": {
    "criteria": {
      "has_iron_ingot": "2026-02-13 00:10:14 +0000"
    },
    "done": true
  },
  "minecraft:recipes/decorations/item_frame": {
    "criteria": {
      "has_leather": "2026-02-13 00:24:56 +0000"
    },
    "done": true
  },
  "nvr:progression/root": {
    "criteria": {
      "requirement": "2026-02-13 00:00:16 +0000"
    },
    "done": true
  },
  "minecraft:recipes/redstone/oak_pressure_plate": {
    "criteria": {
      "has_planks": "2026-02-13 00:01:16 +0000"
    },
    "done": true
  },
  "vanilla_refresh:player/tick": {
    "criteria": {
      "s": "2026-02-13 00:00:15 +0000"
    },
    "done": true
  },
  "touhou_little_maid:give_smart_slab": {
    "criteria": {
      "tick": "2026-02-13 00:00:15 +0000"
    },
    "done": true
  },
  "minecraft:recipes/redstone/oak_door": {
    "criteria": {
      "has_planks": "2026-02-13 00:01:16 +0000"
    },
    "done": true
  },
  "minecraft:recipes/redstone/dispenser": {
    "criteria": {
      "has_bow": "2026-02-13 00:04:39 +0000"
    },
    "done": true
  },
  "minecraft:recipes/redstone/iron_trapdoor": {
    "criteria": {
      "has_iron_ingot": "2026-02-13 00:10:14 +0000"
    },
    "done": true
  },
  "minecraft:adventure/root": {
    "criteria": {
      "killed_something": "2026-02-13 00:04:43 +0000"
    },
    "done": true
  },
  "blood_n_particles:blood_n_particles": {
    "criteria": {
      "requirement": "2026-02-13 00:00:15 +0000"
    },
    "done": true
  },
  "minecraft:end/root": {
    "criteria": {
      "entered_end": "2026-02-13 00:03:31 +0000"
    },
    "done": true
  },
  "minecraft:recipes/building_blocks/oak_planks": {
    "criteria": {
      "has_logs": "2026-02-13 00:00:52 +0000"
    },
    "done": true
  },
  "minecraft:recipes/tools/iron_axe": {
    "criteria": {
      "has_iron_ingot": "2026-02-13 00:10:14 +0000"
    },
    "done": true
  },
  "minecraft:recipes/combat/crossbow": {
    "criteria": {
      "has_iron_ingot": "2026-02-13 00:10:14 +0000"
    },
    "done": true
  },
  "minecraft:adventure/kill_a_mob": {
    "criteria": {
      "minecraft:enderman": "2026-02-13 00:04:43 +0000"
    },
    "done": true
  },
  "minecraft:adventure/adventuring_time": {
    "criteria": {
      "minecraft:deep_dark": "2026-02-13 00:00:25 +0000",
      "minecraft:sparse_jungle": "2026-02-13 00:00:16 +0000"
    },
    "done": false
  },
  "minecraft:recipes/decorations/barrel": {
    "criteria": {
      "has_planks": "2026-02-13 00:01:16 +0000"
    },
    "done": true
  },
  "minecraft:recipes/combat/leather_boots": {
    "criteria": {
      "has_leather": "2026-02-13 00:24:56 +0000"
    },
    "done": true
  },
  "blood_n_particles:almost": {
    "criteria": {
      "requirement": "2026-02-13 00:14:36 +0000"
    },
    "done": true
  },
  "minecraft:husbandry/balanced_diet": {
    "criteria": {
      "bread": "2026-02-13 00:01:31 +0000",
      "enchanted_golden_apple": "2026-02-13 00:12:49 +0000"
    },
    "done": false
  },
  "simplyswords:stars_edge": {
    "criteria": {
      "requirement": "2026-02-13 00:21:17 +0000"
    },
    "done": true
  },
  "minecraft:recipes/building_blocks/oak_wood": {
    "criteria": {
      "has_log": "2026-02-13 00:00:52 +0000"
    },
    "done": true
  },
  "minecraft:recipes/redstone/iron_door": {
    "criteria": {
      "has_iron_ingot": "2026-02-13 00:10:14 +0000"
    },
    "done": true
  },
  "minecraft:recipes/misc/iron_ingot_from_nuggets": {
    "criteria": {
      "has_iron_nugget": "2026-02-13 00:11:39 +0000"
    },
    "done": true
  },
  "minecraft:recipes/redstone/heavy_weighted_pressure_plate": {
    "criteria": {
      "has_iron_ingot": "2026-02-13 00:10:14 +0000"
    },
    "done": true
  },
  "minecraft:story/enter_the_end": {
    "criteria": {
      "entered_end": "2026-02-13 00:03:31 +0000"
    },
    "done": true
  },
  "minecraft:recipes/misc/mojang_banner_pattern": {
    "criteria": {
      "has_enchanted_golden_apple": "2026-02-13 00:02:22 +0000"
    },
    "done": true
  },
  "DataVersion": 3955
}